d3d4/pyavg/__init__.py
d3d4/pyavg/bi_avg.py
d3d4/pyavg/cumulative.py
d3d4/pyavg/exp_smooth.py
d3d4/pyavg/pid.py
d3d4/pyavg/ring_buff.py
d3d4/pyavg/smooth.py
d3d4.pyavg-0.1.2.dist-info/LICENSE
d3d4.pyavg-0.1.2.dist-info/METADATA
d3d4.pyavg-0.1.2.dist-info/WHEEL
d3d4.pyavg-0.1.2.dist-info/top_level.txt
d3d4.pyavg-0.1.2.dist-info/RECORD
