Metadata-Version: 2.1
Name: d3d4.pyavg
Version: 0.1.2
Summary: Average value calculation
License: MIT License
Project-URL: Homepage, https://github.com/ehles/ehles.pyavg
Project-URL: Repository, https://github.com/ehles/ehles.pyavg.git
Keywords: average,avg,stat,pyavg
Requires-Python: >=3.8
License-File: LICENSE
